[
  {
    "id": "123",
    "userName": "sim",
    "email": "sim@test.com",
    "profileImage": "https://bit.ly/3euIgJj",
    "password": "1234",
    "type": "mail",
    "follow": [
      "tea",
      "iu"
    ],
    "bookmark": [
      "1",
      "2",
      "3"
    ],
    "passwordUpdate": null
  },
  {
    "id": "124",
    "userName": "choi",
    "email": "choi@test.com",
    "profileImage": "https://bit.ly/3euIgJj",
    "password": "1234",
    "type": "google",
    "follow": [
      "iu"
    ],
    "bookmark": [
      "1"
    ],
    "passwordUpdate": "2021-05-24 11:42:00"
  },
  {
    "id": "125",
    "userName": "Lee",
    "email": "Lee@test.com",
    "profileImage": "https://bit.ly/3euIgJj",
    "password": "1234",
    "type": "kakao",
    "follow": [
      "v1",
      "j1"
    ],
    "bookmark": [
      "2",
      "1"
    ],
    "passwordUpdate": null
  },
  {
    "id": "126",
    "userName": "Yoo",
    "email": "Yoo@test.com",
    "profileImage": "https://bit.ly/3euIgJj",
    "password": "1234",
    "type": "twiiter",
    "follow": [
      "e1",
      "e2",
      "e3",
      "e4",
      "e5",
      "e6",
      "e7"
    ],
    "bookmark": [
      "3",
      "1"
    ],
    "passwordUpdate": null
  }
]